dbstoreplugin/__init__.py
dbstoreplugin/store/__init__.py
dbstoreplugin/store/artifact/__init__.py
dbstoreplugin/store/artifact/db_artifact_repo.py
dbstoreplugin/store/db/__init__.py
dbstoreplugin/store/db/initial_artifact_store_models.py
mlflow_dbstore-1.0.1.dist-info/LICENSE.txt
mlflow_dbstore-1.0.1.dist-info/METADATA
mlflow_dbstore-1.0.1.dist-info/WHEEL
mlflow_dbstore-1.0.1.dist-info/entry_points.txt
mlflow_dbstore-1.0.1.dist-info/top_level.txt
mlflow_dbstore-1.0.1.dist-info/RECORD
