Metadata-Version: 2.1
Name: mlflow-dbstore
Version: 1.0.1
Summary: Plugin that provides DB Artifact Store functionality for MLflow
Home-page: https://github.com/avflor/mlflow-dbstore
Author: Avrilia Floratou
Author-email: avflor@microsoft.com
License: UNKNOWN
Platform: UNKNOWN
Requires-Dist: mlflow
